async_messages/__init__.py
async_messages/messages.py
async_messages/middleware.py
aoj_django_async_messages-0.3.2.dist-info/AUTHORS
aoj_django_async_messages-0.3.2.dist-info/LICENSE
aoj_django_async_messages-0.3.2.dist-info/METADATA
aoj_django_async_messages-0.3.2.dist-info/WHEEL
aoj_django_async_messages-0.3.2.dist-info/top_level.txt
aoj_django_async_messages-0.3.2.dist-info/RECORD
