Metadata-Version: 2.1
Name: aoj-django-async-messages
Version: 0.3.2
Summary: Send asynchronous messages to users (eg from offline scripts).  Useful for integration with Celery
Home-page: https://github.com/ygowill/django-async-messages
Author: David Winterbottom
Author-email: david.winterbottom@gmail.com
License-File: LICENSE
License-File: AUTHORS
Requires-Dist: django (>=1.2)
